mlserver/__init__.py
mlserver/batch_processing.py
mlserver/batching/__init__.py
mlserver/batching/adaptive.py
mlserver/batching/hooks.py
mlserver/batching/requests.py
mlserver/batching/shape.py
mlserver/cache/__init__.py
mlserver/cache/cache.py
mlserver/cache/local/__init__.py
mlserver/cache/local/local.py
mlserver/cli/__init__.py
mlserver/cli/build.py
mlserver/cli/constants.py
mlserver/cli/init_project.py
mlserver/cli/main.py
mlserver/cli/serve.py
mlserver/cloudevents.py
mlserver/codecs/__init__.py
mlserver/codecs/base.py
mlserver/codecs/base64.py
mlserver/codecs/datetime.py
mlserver/codecs/decorator.py
mlserver/codecs/errors.py
mlserver/codecs/json.py
mlserver/codecs/lists.py
mlserver/codecs/numpy.py
mlserver/codecs/pandas.py
mlserver/codecs/string.py
mlserver/codecs/utils.py
mlserver/context.py
mlserver/env.py
mlserver/errors.py
mlserver/grpc/__init__.py
mlserver/grpc/converters.py
mlserver/grpc/dataplane_pb2.py
mlserver/grpc/dataplane_pb2.pyi
mlserver/grpc/dataplane_pb2_grpc.py
mlserver/grpc/interceptors.py
mlserver/grpc/logging.py
mlserver/grpc/model_repository.py
mlserver/grpc/model_repository_pb2.py
mlserver/grpc/model_repository_pb2.pyi
mlserver/grpc/model_repository_pb2_grpc.py
mlserver/grpc/server.py
mlserver/grpc/servicers.py
mlserver/grpc/utils.py
mlserver/handlers/__init__.py
mlserver/handlers/custom.py
mlserver/handlers/dataplane.py
mlserver/handlers/model_repository.py
mlserver/kafka/__init__.py
mlserver/kafka/errors.py
mlserver/kafka/handlers.py
mlserver/kafka/logging.py
mlserver/kafka/message.py
mlserver/kafka/server.py
mlserver/logging.py
mlserver/metrics/__init__.py
mlserver/metrics/context.py
mlserver/metrics/errors.py
mlserver/metrics/logging.py
mlserver/metrics/prometheus.py
mlserver/metrics/registry.py
mlserver/metrics/server.py
mlserver/middleware.py
mlserver/model.py
mlserver/parallel/__init__.py
mlserver/parallel/dispatcher.py
mlserver/parallel/errors.py
mlserver/parallel/logging.py
mlserver/parallel/messages.py
mlserver/parallel/model.py
mlserver-1.7.0.dist-info/LICENSE
mlserver-1.7.0.dist-info/METADATA
mlserver-1.7.0.dist-info/WHEEL
mlserver-1.7.0.dist-info/entry_points.txt
mlserver-1.7.0.dist-info/RECORD
