Metadata-Version: 2.3
Name: mlserver
Version: 1.7.0
Summary: MLServer
License: Apache-2.0
Author: Seldon Technologies Ltd.
Author-email: hello@seldon.io
Requires-Python: >=3.9,<3.13
Classifier: License :: OSI Approved :: Apache Software License
Classifier: Operating System :: MacOS
Classifier: Operating System :: POSIX
Classifier: Programming Language :: Python :: 3
Classifier: Programming Language :: Python :: 3.9
Classifier: Programming Language :: Python :: 3.10
Classifier: Programming Language :: Python :: 3.11
Classifier: Programming Language :: Python :: 3.12
Requires-Dist: aiofiles
Requires-Dist: aiokafka
Requires-Dist: click
Requires-Dist: fastapi (>=0.88.0,!=0.89.0,<0.116.0)
Requires-Dist: gevent
Requires-Dist: geventhttpclient
Requires-Dist: grpcio
Requires-Dist: importlib-resources (>=5.12,<7.0)
Requires-Dist: numpy
Requires-Dist: opentelemetry-exporter-otlp-proto-grpc (>=1.22.0,<2.0.0)
Requires-Dist: opentelemetry-instrumentation-fastapi (>=0.43b0)
Requires-Dist: opentelemetry-instrumentation-grpc (>=0.43b0)
Requires-Dist: opentelemetry-sdk (>=1.22.0,<2.0.0)
Requires-Dist: orjson
Requires-Dist: pandas
Requires-Dist: protobuf
Requires-Dist: py-grpc-prometheus
Requires-Dist: pydantic (>=2.7.1,<3.0.0)
Requires-Dist: pydantic-settings (>=2.3.0,<3.0.0)
Requires-Dist: python-dotenv
Requires-Dist: python-multipart
Requires-Dist: starlette-exporter
Requires-Dist: tritonclient[http] (>=2.42)
Requires-Dist: uvicorn
Requires-Dist: uvloop ; sys_platform != "win32" and sys_platform != "cygwin" and platform_python_implementation != "PyPy"
